Metadata-Version: 1.0
Name: maxattacks-distributions
Version: 0.1
Summary: Gaussian and Binomial distributions
Home-page: UNKNOWN
Author: Maximilian Kemper
Author-email: bienemaya1337@gmx.de
License: UNKNOWN
Platform: UNKNOWN
